{
  "address": "https://www.pinterest.com/pin/88101736430756821/",
  "dataMode": "json",
  "hotlinkProtected": false,
  "connectionTimeOut": -1,
  "otherPropertiesMap": {
    "CustomFolderName": "basketfuls/bedrooms",
    "CustomFileName": "88101736430756821",
    "FileExtensionHandleMethod": "workoutExtension",
    "_json": {
      "id": "88101736430756821",
      "url": "https://www.pinterest.com/pin/88101736430756821/",
      "type": "pin",
      "title": "",
      "gridTitle": "STARFISH DESIGNS",
      "description": "pink and shabby",
      "link": "http://starfishdesigns-pcb.blogspot.com/search?updated-max=2011-01-06T10:27:00-08:00&max-results=230",
      "category": "",
      "isStoryPin": false,
      "isCarousel": false,
      "doneByMe": false,
      "favouritedByMe": false,
      "isRepin": true,
      "storyPinItemCount": 0,
      "carouselItemCount": 0,
      "repinCount": 0,
      "favouriteUserCount": 0,
      "board": {
        "url": "https://www.pinterest.com/basketfuls/bedrooms/",
        "name": "Bedrooms",
        "type": "board",
        "ownerUsername": "basketfuls",
        "ownerName": "S. L.",
        "ownerUrl": "https://www.pinterest.com/basketfuls/"
      },
      "media": [
        {
          "url": "https://i.pinimg.com/originals/ef/c5/32/efc532e72b0085436fad4217491a790a.jpg",
          "type": "image"
        }
      ]
    }
  }
}