{
  "address": "https://www.pinterest.com/pin/88101736448300511/",
  "dataMode": "json",
  "hotlinkProtected": false,
  "connectionTimeOut": -1,
  "otherPropertiesMap": {
    "CustomFolderName": "basketfuls/cute-kitchens",
    "CustomFileName": "88101736448300511",
    "FileExtensionHandleMethod": "workoutExtension",
    "_json": {
      "id": "88101736448300511",
      "url": "https://www.pinterest.com/pin/88101736448300511/",
      "type": "pin",
      "title": "",
      "gridTitle": "SFGirlByBay | Substack",
      "description": "nest pretty things | sfgirlbybay",
      "link": "http://www.sfgirlbybay.com/2014/04/17/studio-spaces-nest-pretty-things/",
      "category": "",
      "isStoryPin": false,
      "isCarousel": false,
      "doneByMe": false,
      "favouritedByMe": false,
      "isRepin": true,
      "storyPinItemCount": 0,
      "carouselItemCount": 0,
      "repinCount": 0,
      "favouriteUserCount": 0,
      "creator": {
        "username": "sasibella",
        "url": "https://www.pinterest.com/sasibella/",
        "name": "Sasibella"
      },
      "board": {
        "url": "https://www.pinterest.com/basketfuls/cute-kitchens/",
        "name": "Cute Kitchens",
        "type": "board",
        "ownerUsername": "basketfuls",
        "ownerName": "S. L.",
        "ownerUrl": "https://www.pinterest.com/basketfuls/"
      },
      "media": [
        {
          "url": "https://i.pinimg.com/originals/2c/8d/e1/2c8de16c424ff80861a618694652ac79.jpg",
          "type": "image"
        }
      ]
    }
  }
}