{
  "address": "https://www.pinterest.com/pin/88101736438167634/",
  "dataMode": "json",
  "hotlinkProtected": false,
  "connectionTimeOut": -1,
  "otherPropertiesMap": {
    "CustomFolderName": "basketfuls/preserving-food",
    "CustomFileName": "88101736438167634",
    "FileExtensionHandleMethod": "workoutExtension",
    "_json": {
      "id": "88101736438167634",
      "url": "https://www.pinterest.com/pin/88101736438167634/",
      "type": "pin",
      "title": "",
      "gridTitle": "Using an Electric Roaster While Canning",
      "description": "Using an Electric Roaster While Canning",
      "link": "http://paulaoretirement.blogspot.com/2012/08/using-electric-roaster-while-canning.html",
      "category": "",
      "isStoryPin": false,
      "isCarousel": false,
      "doneByMe": false,
      "favouritedByMe": false,
      "isRepin": true,
      "storyPinItemCount": 0,
      "carouselItemCount": 0,
      "repinCount": 0,
      "favouriteUserCount": 0,
      "board": {
        "url": "https://www.pinterest.com/basketfuls/preserving-food/",
        "name": "Preserving Food",
        "type": "board",
        "ownerUsername": "basketfuls",
        "ownerName": "S. L.",
        "ownerUrl": "https://www.pinterest.com/basketfuls/"
      },
      "media": [
        {
          "url": "https://i.pinimg.com/originals/5e/cf/f2/5ecff209e6a717e36a1d05c760c71c87.jpg",
          "type": "image"
        }
      ]
    }
  }
}