{
  "address": "https://www.pinterest.com/pin/88101736435983816/",
  "dataMode": "json",
  "hotlinkProtected": false,
  "connectionTimeOut": -1,
  "otherPropertiesMap": {
    "CustomFolderName": "basketfuls/afternoon-tea",
    "CustomFileName": "88101736435983816",
    "FileExtensionHandleMethod": "workoutExtension",
    "_json": {
      "id": "88101736435983816",
      "url": "https://www.pinterest.com/pin/88101736435983816/",
      "type": "pin",
      "title": "",
      "gridTitle": "Farm table and all white centerpiece",
      "description": "Farm table and all white #Romantic Life Style| http://my-romantic-life-styles.blogspot.com",
      "link": "http://my-romantic-life-styles.blogspot.com/2013/09/farm-table-and-all-white-centerpiece.html",
      "category": "",
      "isStoryPin": false,
      "isCarousel": false,
      "doneByMe": false,
      "favouritedByMe": false,
      "isRepin": true,
      "storyPinItemCount": 0,
      "carouselItemCount": 0,
      "repinCount": 0,
      "favouriteUserCount": 0,
      "board": {
        "url": "https://www.pinterest.com/basketfuls/afternoon-tea/",
        "name": "Afternoon Tea",
        "type": "board",
        "ownerUsername": "basketfuls",
        "ownerName": "S. L.",
        "ownerUrl": "https://www.pinterest.com/basketfuls/"
      },
      "media": [
        {
          "url": "https://i.pinimg.com/originals/1d/34/7c/1d347cebecbf2243bceb44f845badbb1.jpg",
          "type": "image"
        }
      ]
    }
  }
}