{
  "address": "https://www.pinterest.com/pin/88101736446468899/",
  "dataMode": "json",
  "hotlinkProtected": false,
  "connectionTimeOut": -1,
  "otherPropertiesMap": {
    "CustomFolderName": "basketfuls/afternoon-tea",
    "CustomFileName": "88101736446468899",
    "FileExtensionHandleMethod": "workoutExtension",
    "_json": {
      "id": "88101736446468899",
      "url": "https://www.pinterest.com/pin/88101736446468899/",
      "type": "pin",
      "title": "",
      "gridTitle": "Tea House - North Texas area Top 5 - 2017 Dallas A-List",
      "description": "Dallas A-List's Best Tea House - Top 5 (2013)",
      "link": "http://dallas.cityvoter.com/best/tea-house/specialty-food-and-drink/north-texas/slideshow",
      "category": "",
      "isStoryPin": false,
      "isCarousel": false,
      "doneByMe": false,
      "favouritedByMe": false,
      "isRepin": true,
      "storyPinItemCount": 0,
      "carouselItemCount": 0,
      "repinCount": 0,
      "favouriteUserCount": 0,
      "board": {
        "url": "https://www.pinterest.com/basketfuls/afternoon-tea/",
        "name": "Afternoon Tea",
        "type": "board",
        "ownerUsername": "basketfuls",
        "ownerName": "S. L.",
        "ownerUrl": "https://www.pinterest.com/basketfuls/"
      },
      "media": [
        {
          "url": "https://i.pinimg.com/originals/70/6b/a8/706ba8834dfc710d0a82c1ecbeed813c.jpg",
          "type": "image"
        }
      ]
    }
  }
}