{
  "address": "https://www.pinterest.com/pin/88101736452318946/",
  "dataMode": "json",
  "hotlinkProtected": false,
  "connectionTimeOut": -1,
  "otherPropertiesMap": {
    "CustomFolderName": "basketfuls/womenchurch",
    "CustomFileName": "88101736452318946",
    "FileExtensionHandleMethod": "workoutExtension",
    "_json": {
      "id": "88101736452318946",
      "url": "https://www.pinterest.com/pin/88101736452318946/",
      "type": "pin",
      "title": "",
      "gridTitle": "",
      "description": " ",
      "link": "https://s-media-cache-ak0.pinimg.com/736x/6b/b5/c1/6bb5c148aaea7527cbc7ae9032f356e2.jpg",
      "category": "",
      "isStoryPin": false,
      "isCarousel": false,
      "doneByMe": false,
      "favouritedByMe": false,
      "isRepin": true,
      "storyPinItemCount": 0,
      "carouselItemCount": 0,
      "repinCount": 0,
      "favouriteUserCount": 0,
      "board": {
        "url": "https://www.pinterest.com/basketfuls/womenchurch/",
        "name": "Women/Church",
        "type": "board",
        "ownerUsername": "basketfuls",
        "ownerName": "S. L.",
        "ownerUrl": "https://www.pinterest.com/basketfuls/"
      },
      "media": [
        {
          "url": "https://i.pinimg.com/originals/09/aa/cb/09aacb6a55123abff954694acfb5c6ed.jpg",
          "type": "image"
        }
      ]
    }
  }
}