{
  "address": "https://www.pinterest.com/pin/88101736441457906/",
  "dataMode": "json",
  "hotlinkProtected": false,
  "connectionTimeOut": -1,
  "otherPropertiesMap": {
    "CustomFolderName": "basketfuls/chinese-foodrecipes",
    "CustomFileName": "88101736441457906",
    "FileExtensionHandleMethod": "workoutExtension",
    "_json": {
      "id": "88101736441457906",
      "url": "https://www.pinterest.com/pin/88101736441457906/",
      "type": "pin",
      "title": "",
      "gridTitle": "ลงทะเบียนรับเครดิตฟรี 49 สำหรับสมาชิกใหม่",
      "description": "For all those who love Chinese food like me and who are always ready to eat Chinese food. This is the most easy and tasty chili chicken you ever have. Try it. image courtesy: healthy recipes Ingredients Of Chinese Chili Chicken 1/2 kg boneless chicken in cubes For Marinade 1/2 tsp. salt 1/2 tsp. black …",
      "link": "http://www.neelscorner.com/chinese-chili-chicken-recipe-by-shireen-anwar/",
      "category": "",
      "isStoryPin": false,
      "isCarousel": false,
      "doneByMe": false,
      "favouritedByMe": false,
      "isRepin": true,
      "storyPinItemCount": 0,
      "carouselItemCount": 0,
      "repinCount": 0,
      "favouriteUserCount": 0,
      "board": {
        "url": "https://www.pinterest.com/basketfuls/chinese-foodrecipes/",
        "name": "Chinese Food/Recipes",
        "type": "board",
        "ownerUsername": "basketfuls",
        "ownerName": "S. L.",
        "ownerUrl": "https://www.pinterest.com/basketfuls/"
      },
      "media": [
        {
          "url": "https://i.pinimg.com/originals/c4/ce/5b/c4ce5bf6cb2e3579530186ebb5b93b41.jpg",
          "type": "image"
        }
      ]
    }
  }
}