{
  "address": "https://www.pinterest.com/pin/88101736447944422/",
  "dataMode": "json",
  "hotlinkProtected": false,
  "connectionTimeOut": -1,
  "otherPropertiesMap": {
    "CustomFolderName": "basketfuls/artpicturespretty-bits",
    "CustomFileName": "88101736447944422",
    "FileExtensionHandleMethod": "workoutExtension",
    "_json": {
      "id": "88101736447944422",
      "url": "https://www.pinterest.com/pin/88101736447944422/",
      "type": "pin",
      "title": "",
      "gridTitle": "F024 Cleaning Rabbit",
      "description": "Bug Art F024 Cleaning Rabbit greetings card",
      "link": "https://bugart.co.uk/product/f024-cleaning-rabbit/",
      "category": "",
      "isStoryPin": false,
      "isCarousel": false,
      "doneByMe": false,
      "favouritedByMe": false,
      "isRepin": true,
      "storyPinItemCount": 0,
      "carouselItemCount": 0,
      "repinCount": 0,
      "favouriteUserCount": 0,
      "board": {
        "url": "https://www.pinterest.com/basketfuls/artpicturespretty-bits/",
        "name": "Art/Pictures/Pretty bits",
        "type": "board",
        "ownerUsername": "basketfuls",
        "ownerName": "S. L.",
        "ownerUrl": "https://www.pinterest.com/basketfuls/"
      },
      "media": [
        {
          "url": "https://i.pinimg.com/originals/f1/52/4b/f1524bc390886db86dad31e1b4fceea9.jpg",
          "type": "image"
        }
      ]
    }
  }
}