{
  "address": "https://www.pinterest.com/pin/88101736452441736/",
  "dataMode": "json",
  "hotlinkProtected": false,
  "connectionTimeOut": -1,
  "otherPropertiesMap": {
    "CustomFolderName": "basketfuls/painted-furniture-etc",
    "CustomFileName": "88101736452441736",
    "FileExtensionHandleMethod": "workoutExtension",
    "_json": {
      "id": "88101736452441736",
      "url": "https://www.pinterest.com/pin/88101736452441736/",
      "type": "pin",
      "title": "",
      "gridTitle": "3 Things to Know Before Painting Knobs & Other Hardware - Painted Furniture Ideas",
      "description": "Painting knobs, pulls and other metal hardware is a great way to fix up fixtures without the added expense of replacing them. There are a few benefits to painting hardware over buying new. One, is that some older knobs and pulls have character & style that are near impossible to …",
      "link": "http://paintedfurnitureideas.com/3-things-to-know-before-painting-knobs-other-hardware/",
      "category": "",
      "isStoryPin": false,
      "isCarousel": false,
      "doneByMe": false,
      "favouritedByMe": false,
      "isRepin": true,
      "storyPinItemCount": 0,
      "carouselItemCount": 0,
      "repinCount": 0,
      "favouriteUserCount": 0,
      "board": {
        "url": "https://www.pinterest.com/basketfuls/painted-furniture-etc/",
        "name": "Painted Furniture etc",
        "type": "board",
        "ownerUsername": "basketfuls",
        "ownerName": "S. L.",
        "ownerUrl": "https://www.pinterest.com/basketfuls/"
      },
      "media": [
        {
          "url": "https://i.pinimg.com/originals/b4/f9/a4/b4f9a47d8a11d27aac8f6dec3d5e765b.jpg",
          "type": "image"
        }
      ]
    }
  }
}