{
  "address": "https://www.pinterest.com/pin/88101736445297316/",
  "dataMode": "json",
  "hotlinkProtected": false,
  "connectionTimeOut": -1,
  "otherPropertiesMap": {
    "CustomFolderName": "basketfuls/ice-cream",
    "CustomFileName": "88101736445297316",
    "FileExtensionHandleMethod": "workoutExtension",
    "_json": {
      "id": "88101736445297316",
      "url": "https://www.pinterest.com/pin/88101736445297316/",
      "type": "pin",
      "title": "",
      "gridTitle": "How Social Media Has Made NYC’s Ice-Cream Scene More Innovative Than Ever",
      "description": "Thai rolled ice cream and shaved snow are taking over.",
      "link": "http://www.grubstreet.com/2016/04/social-media-ice-cream-scene.html?utm_source=Sailthru&utm_medium=email&utm_campaign=Grub%20Street%20-%202016-04-21&utm_term=Subscription%20List%20-%20Grub%20Street%20(1%20Year)",
      "category": "",
      "isStoryPin": false,
      "isCarousel": false,
      "doneByMe": false,
      "favouritedByMe": false,
      "isRepin": true,
      "storyPinItemCount": 0,
      "carouselItemCount": 0,
      "repinCount": 3,
      "favouriteUserCount": 0,
      "board": {
        "url": "https://www.pinterest.com/basketfuls/ice-cream/",
        "name": "Ice cream",
        "type": "board",
        "ownerUsername": "basketfuls",
        "ownerName": "S. L.",
        "ownerUrl": "https://www.pinterest.com/basketfuls/"
      },
      "media": [
        {
          "url": "https://i.pinimg.com/originals/b2/63/16/b26316d2ec76638c805d51611c3abe4b.jpg",
          "type": "image"
        }
      ]
    }
  }
}