{
  "address": "https://www.pinterest.com/pin/88101736434790036/",
  "dataMode": "json",
  "hotlinkProtected": false,
  "connectionTimeOut": -1,
  "otherPropertiesMap": {
    "CustomFolderName": "basketfuls/potato-recipes",
    "CustomFileName": "88101736434790036",
    "FileExtensionHandleMethod": "workoutExtension",
    "_json": {
      "id": "88101736434790036",
      "url": "https://www.pinterest.com/pin/88101736434790036/",
      "type": "pin",
      "title": "",
      "gridTitle": "Cheese and Cream Baked Potatoes",
      "description": "Cheese and Cream Baked Potatoes",
      "link": "http://www.flickr.com/photos/heatherchristo/8594450488/",
      "category": "",
      "isStoryPin": false,
      "isCarousel": false,
      "doneByMe": false,
      "favouritedByMe": false,
      "isRepin": true,
      "storyPinItemCount": 0,
      "carouselItemCount": 0,
      "repinCount": 0,
      "favouriteUserCount": 0,
      "board": {
        "url": "https://www.pinterest.com/basketfuls/potato-recipes/",
        "name": "Potato Recipes",
        "type": "board",
        "ownerUsername": "basketfuls",
        "ownerName": "S. L.",
        "ownerUrl": "https://www.pinterest.com/basketfuls/"
      },
      "media": [
        {
          "url": "https://i.pinimg.com/originals/2f/98/9b/2f989b5f5193aab7f1c37902b39538b3.jpg",
          "type": "image"
        }
      ]
    }
  }
}