{
  "address": "https://www.pinterest.com/pin/88101736437047382/",
  "dataMode": "json",
  "hotlinkProtected": false,
  "connectionTimeOut": -1,
  "otherPropertiesMap": {
    "CustomFolderName": "basketfuls/brewing",
    "CustomFileName": "88101736437047382",
    "FileExtensionHandleMethod": "workoutExtension",
    "_json": {
      "id": "88101736437047382",
      "url": "https://www.pinterest.com/pin/88101736437047382/",
      "type": "pin",
      "title": "",
      "gridTitle": "How to Make Hard Cider - Wine Making and Beer Brewing Blog - Adventures in Homebrewing",
      "description": "Making Hard Cider At Home (5 Gallon Recipe) - Home Brewing Beer | E. C. Kraus",
      "link": "http://blog.eckraus.com/blog/home-brewing-beer-2/making-hard-cider-at-home?trk_msg=86ASEVQPQNG4J3C9QH94CM63EC&trk_contact=0DBK0C1O5SH81QM22LU5GQOLG0&utm_source=Listrak&utm_medium=Email&utm_term=Article+2+-+Title&utm_campaign=Beermaking+Info+Update+(Sept.+21+-+Sept.+27)",
      "category": "",
      "isStoryPin": false,
      "isCarousel": false,
      "doneByMe": false,
      "favouritedByMe": false,
      "isRepin": true,
      "storyPinItemCount": 0,
      "carouselItemCount": 0,
      "repinCount": 0,
      "favouriteUserCount": 0,
      "board": {
        "url": "https://www.pinterest.com/basketfuls/brewing/",
        "name": "Brewing",
        "type": "board",
        "ownerUsername": "basketfuls",
        "ownerName": "S. L.",
        "ownerUrl": "https://www.pinterest.com/basketfuls/"
      },
      "media": [
        {
          "url": "https://i.pinimg.com/originals/98/a6/d0/98a6d062580265a95820471b745cd25f.jpg",
          "type": "image"
        }
      ]
    }
  }
}