{
  "address": "https://www.pinterest.com/pin/88101736437027152/",
  "dataMode": "json",
  "hotlinkProtected": false,
  "connectionTimeOut": -1,
  "otherPropertiesMap": {
    "CustomFolderName": "basketfuls/words",
    "CustomFileName": "88101736437027152",
    "FileExtensionHandleMethod": "workoutExtension",
    "_json": {
      "id": "88101736437027152",
      "url": "https://www.pinterest.com/pin/88101736437027152/",
      "type": "pin",
      "title": "",
      "gridTitle": "",
      "description": " ",
      "category": "",
      "isStoryPin": false,
      "isCarousel": false,
      "doneByMe": false,
      "favouritedByMe": false,
      "isRepin": true,
      "storyPinItemCount": 0,
      "carouselItemCount": 0,
      "repinCount": 1,
      "favouriteUserCount": 0,
      "board": {
        "url": "https://www.pinterest.com/basketfuls/words/",
        "name": "Words",
        "type": "board",
        "ownerUsername": "basketfuls",
        "ownerName": "S. L.",
        "ownerUrl": "https://www.pinterest.com/basketfuls/"
      },
      "media": [
        {
          "url": "https://i.pinimg.com/originals/78/e7/d2/78e7d289be60e3dd9f10ee20b34a3aa3.jpg",
          "type": "image"
        }
      ]
    }
  }
}