{
  "address": "https://www.pinterest.com/pin/88101736441768060/",
  "dataMode": "json",
  "hotlinkProtected": false,
  "connectionTimeOut": -1,
  "otherPropertiesMap": {
    "CustomFolderName": "basketfuls/vegan-and-ish",
    "CustomFileName": "88101736441768060",
    "FileExtensionHandleMethod": "workoutExtension",
    "_json": {
      "id": "88101736441768060",
      "url": "https://www.pinterest.com/pin/88101736441768060/",
      "type": "pin",
      "title": "",
      "gridTitle": "Contact Support",
      "description": "This recipe serves as a perfect substitute for liver pâté, and it’s entirely plant-based to-boot. Serve this as an appetizer at your next get-together and I guarantee it will be gone as quick as you serve it.  Ingredients:  About 2.5 cups of of cooked green lentils (use green as they stay quite firm). If using dry, use … … Continue reading →",
      "link": "http://veganomical.com/2014/11/22/liverless-lentil-pate/",
      "category": "",
      "isStoryPin": false,
      "isCarousel": false,
      "doneByMe": false,
      "favouritedByMe": false,
      "isRepin": true,
      "storyPinItemCount": 0,
      "carouselItemCount": 0,
      "repinCount": 0,
      "favouriteUserCount": 0,
      "board": {
        "url": "https://www.pinterest.com/basketfuls/vegan-and-ish/",
        "name": "Vegan and ish",
        "type": "board",
        "ownerUsername": "basketfuls",
        "ownerName": "S. L.",
        "ownerUrl": "https://www.pinterest.com/basketfuls/"
      },
      "media": [
        {
          "url": "https://i.pinimg.com/originals/ff/e9/a5/ffe9a5795c8b3680b89e987e3f4da345.jpg",
          "type": "image"
        }
      ]
    }
  }
}