{
  "address": "https://www.pinterest.com/pin/88101736445763252/",
  "dataMode": "json",
  "hotlinkProtected": false,
  "connectionTimeOut": -1,
  "otherPropertiesMap": {
    "CustomFolderName": "basketfuls/agnes-st",
    "CustomFileName": "88101736445763252",
    "FileExtensionHandleMethod": "workoutExtension",
    "_json": {
      "id": "88101736445763252",
      "url": "https://www.pinterest.com/pin/88101736445763252/",
      "type": "pin",
      "title": "",
      "gridTitle": "",
      "description": "DIY shoe rack",
      "category": "",
      "isStoryPin": false,
      "isCarousel": false,
      "doneByMe": false,
      "favouritedByMe": false,
      "isRepin": true,
      "storyPinItemCount": 0,
      "carouselItemCount": 0,
      "repinCount": 0,
      "favouriteUserCount": 0,
      "board": {
        "url": "https://www.pinterest.com/basketfuls/agnes-st/",
        "name": "Agnes st",
        "type": "board",
        "ownerUsername": "basketfuls",
        "ownerName": "S. L.",
        "ownerUrl": "https://www.pinterest.com/basketfuls/"
      },
      "media": [
        {
          "url": "https://i.pinimg.com/originals/7c/da/68/7cda68404cd5420d28aee96fa0f36404.jpg",
          "type": "image"
        }
      ]
    }
  }
}