{
  "address": "https://www.pinterest.com/pin/88101736452583456/",
  "dataMode": "json",
  "hotlinkProtected": false,
  "connectionTimeOut": -1,
  "otherPropertiesMap": {
    "CustomFolderName": "basketfuls/agnes-st",
    "CustomFileName": "88101736452583456",
    "FileExtensionHandleMethod": "workoutExtension",
    "_json": {
      "id": "88101736452583456",
      "url": "https://www.pinterest.com/pin/88101736452583456/",
      "type": "pin",
      "title": "",
      "gridTitle": "14 expert renovation tips to know before you start",
      "description": "Put down the hammer! Before you start your major renovation, here's a few things the experts wish you knew...",
      "link": "https://www.homestolove.com.au/before-you-start-renovation-advice-15551",
      "category": "",
      "isStoryPin": false,
      "isCarousel": false,
      "doneByMe": false,
      "favouritedByMe": false,
      "isRepin": true,
      "storyPinItemCount": 0,
      "carouselItemCount": 0,
      "repinCount": 0,
      "favouriteUserCount": 0,
      "board": {
        "url": "https://www.pinterest.com/basketfuls/agnes-st/",
        "name": "Agnes st",
        "type": "board",
        "ownerUsername": "basketfuls",
        "ownerName": "S. L.",
        "ownerUrl": "https://www.pinterest.com/basketfuls/"
      },
      "media": [
        {
          "url": "https://i.pinimg.com/originals/7f/a6/30/7fa630b032d38082bbf1ae402399e3a3.png",
          "type": "image"
        }
      ]
    }
  }
}