{
  "address": "https://www.pinterest.com/pin/88101736451826419/",
  "dataMode": "json",
  "hotlinkProtected": false,
  "connectionTimeOut": -1,
  "otherPropertiesMap": {
    "CustomFolderName": "basketfuls/for-linda",
    "CustomFileName": "88101736451826419",
    "FileExtensionHandleMethod": "workoutExtension",
    "_json": {
      "id": "88101736451826419",
      "url": "https://www.pinterest.com/pin/88101736451826419/",
      "type": "pin",
      "title": "",
      "gridTitle": "YENİ DEKOPAJ RESİMLERİ",
      "description": "Soma faciası nedeniyle acı dolu günler geçirdik ve hala kalbimizin üstündeki ağırlık kalkmadı fakat hayat devam ediyor ve çalışmak zorundayı...",
      "link": "https://nestug.blogspot.com.tr/2014/05/yeni-dekopaj-resimleri.html?m=1",
      "category": "",
      "isStoryPin": false,
      "isCarousel": false,
      "doneByMe": false,
      "favouritedByMe": false,
      "isRepin": true,
      "storyPinItemCount": 0,
      "carouselItemCount": 0,
      "repinCount": 0,
      "favouriteUserCount": 0,
      "board": {
        "url": "https://www.pinterest.com/basketfuls/for-linda/",
        "name": "For Linda",
        "type": "board",
        "ownerUsername": "basketfuls",
        "ownerName": "S. L.",
        "ownerUrl": "https://www.pinterest.com/basketfuls/"
      },
      "media": [
        {
          "url": "https://i.pinimg.com/originals/96/5f/7a/965f7a22c6aaf70de89cadd3c549258f.jpg",
          "type": "image"
        }
      ]
    }
  }
}