{
  "address": "https://www.pinterest.com/pin/88101736437893048/",
  "dataMode": "json",
  "hotlinkProtected": false,
  "connectionTimeOut": -1,
  "otherPropertiesMap": {
    "CustomFolderName": "basketfuls/rice",
    "CustomFileName": "88101736437893048",
    "FileExtensionHandleMethod": "workoutExtension",
    "_json": {
      "id": "88101736437893048",
      "url": "https://www.pinterest.com/pin/88101736437893048/",
      "type": "pin",
      "title": "",
      "gridTitle": "Risotto alla milanese (Milanese-Style Risotto)",
      "description": "Risotto alla milanese",
      "link": "http://memoriediangelina.com/2011/01/23/risotto-alla-milanese/",
      "category": "",
      "isStoryPin": false,
      "isCarousel": false,
      "doneByMe": false,
      "favouritedByMe": false,
      "isRepin": true,
      "storyPinItemCount": 0,
      "carouselItemCount": 0,
      "repinCount": 0,
      "favouriteUserCount": 0,
      "board": {
        "url": "https://www.pinterest.com/basketfuls/rice/",
        "name": "Rice",
        "type": "board",
        "ownerUsername": "basketfuls",
        "ownerName": "S. L.",
        "ownerUrl": "https://www.pinterest.com/basketfuls/"
      },
      "media": [
        {
          "url": "https://i.pinimg.com/originals/d8/cf/3a/d8cf3ab497acce7495f28320eb294363.jpg",
          "type": "image"
        }
      ]
    }
  }
}