{
  "address": "https://www.pinterest.com/pin/88101736436542886/",
  "dataMode": "json",
  "hotlinkProtected": false,
  "connectionTimeOut": -1,
  "otherPropertiesMap": {
    "CustomFolderName": "basketfuls/cottage-christmas",
    "CustomFileName": "88101736436542886",
    "FileExtensionHandleMethod": "workoutExtension",
    "_json": {
      "id": "88101736436542886",
      "url": "https://www.pinterest.com/pin/88101736436542886/",
      "type": "pin",
      "title": "",
      "gridTitle": "Moving Company Quotes & Tips to Plan Your Move | MYMOVE",
      "description": "A beautifully stylish Christmas themed living room.",
      "link": "http://freshome.com/2011/12/05/33-christmas-decorations-ideas-bringing-the-christmas-spirit-into-your-living-room",
      "category": "",
      "isStoryPin": false,
      "isCarousel": false,
      "doneByMe": false,
      "favouritedByMe": false,
      "isRepin": true,
      "storyPinItemCount": 0,
      "carouselItemCount": 0,
      "repinCount": 0,
      "favouriteUserCount": 0,
      "board": {
        "url": "https://www.pinterest.com/basketfuls/cottage-christmas/",
        "name": "Cottage Christmas",
        "type": "board",
        "ownerUsername": "basketfuls",
        "ownerName": "S. L.",
        "ownerUrl": "https://www.pinterest.com/basketfuls/"
      },
      "media": [
        {
          "url": "https://i.pinimg.com/originals/68/b3/d5/68b3d53907df3f1eb3de8621fe6ef2ba.jpg",
          "type": "image"
        }
      ]
    }
  }
}