{
  "address": "https://www.pinterest.com/pin/88101736436305695/",
  "dataMode": "json",
  "hotlinkProtected": false,
  "connectionTimeOut": -1,
  "otherPropertiesMap": {
    "CustomFolderName": "basketfuls/health-related",
    "CustomFileName": "88101736436305695",
    "FileExtensionHandleMethod": "workoutExtension",
    "_json": {
      "id": "88101736436305695",
      "url": "https://www.pinterest.com/pin/88101736436305695/",
      "type": "pin",
      "title": "",
      "gridTitle": "Natural Wellness Articles",
      "description": "Surprising discovery: HIV hides in gut, evading eradication",
      "link": "http://www.prohealth.com/library/showarticle.cfm?libid=19192#sthash.39EJ09Lh.qjtu",
      "category": "",
      "isStoryPin": false,
      "isCarousel": false,
      "doneByMe": false,
      "favouritedByMe": false,
      "isRepin": true,
      "storyPinItemCount": 0,
      "carouselItemCount": 0,
      "repinCount": 0,
      "favouriteUserCount": 0,
      "board": {
        "url": "https://www.pinterest.com/basketfuls/health-related/",
        "name": "Health Related",
        "type": "board",
        "ownerUsername": "basketfuls",
        "ownerName": "S. L.",
        "ownerUrl": "https://www.pinterest.com/basketfuls/"
      },
      "media": [
        {
          "url": "https://i.pinimg.com/originals/12/6f/8d/126f8dc29a689bd2eda104f5ea2ab31c.jpg",
          "type": "image"
        }
      ]
    }
  }
}