{
  "address": "https://www.pinterest.com/pin/88101736443476078/",
  "dataMode": "json",
  "hotlinkProtected": false,
  "connectionTimeOut": -1,
  "otherPropertiesMap": {
    "CustomFolderName": "basketfuls/your-pinterest-likes",
    "CustomFileName": "88101736443476078",
    "FileExtensionHandleMethod": "workoutExtension",
    "_json": {
      "id": "88101736443476078",
      "url": "https://www.pinterest.com/pin/88101736443476078/",
      "type": "pin",
      "title": "",
      "gridTitle": "Homesessive",
      "description": "CLEANING: They tried, tested and compared homemade cleaning solutions to store bought chemical ones and made a list of the best homemade recipes to use.  Great source!",
      "link": "http://www.shelterpop.com/2010/12/01/homemade-cleaning-solutions/",
      "category": "",
      "isStoryPin": false,
      "isCarousel": false,
      "doneByMe": false,
      "favouritedByMe": false,
      "isRepin": true,
      "storyPinItemCount": 0,
      "carouselItemCount": 0,
      "repinCount": 0,
      "favouriteUserCount": 0,
      "board": {
        "url": "https://www.pinterest.com/basketfuls/your-pinterest-likes/",
        "name": "Your Pinterest likes",
        "type": "board",
        "ownerUsername": "basketfuls",
        "ownerName": "S. L.",
        "ownerUrl": "https://www.pinterest.com/basketfuls/"
      },
      "media": [
        {
          "url": "https://i.pinimg.com/originals/5c/c1/2d/5cc12d64bea8c32630e4adb35afde8d9.jpg",
          "type": "image"
        }
      ]
    }
  }
}