{
  "address": "https://www.pinterest.com/pin/88101736453405555/",
  "dataMode": "json",
  "hotlinkProtected": false,
  "connectionTimeOut": -1,
  "otherPropertiesMap": {
    "CustomFolderName": "basketfuls/cake-decorating/frostingicing-recipes",
    "CustomFileName": "88101736453405555",
    "FileExtensionHandleMethod": "workoutExtension",
    "_json": {
      "id": "88101736453405555",
      "url": "https://www.pinterest.com/pin/88101736453405555/",
      "type": "pin",
      "title": "",
      "gridTitle": "Lemon Ganache - The Littlest Crumb",
      "description": " ",
      "link": "https://thelittlestcrumb.com/lemon-ganache/",
      "category": "",
      "isStoryPin": false,
      "isCarousel": false,
      "doneByMe": false,
      "favouritedByMe": false,
      "isRepin": true,
      "storyPinItemCount": 0,
      "carouselItemCount": 0,
      "repinCount": 0,
      "favouriteUserCount": 0,
      "board": {
        "url": "https://www.pinterest.com/basketfuls/cake-decorating/",
        "name": "Cake Decorating",
        "type": "board",
        "ownerUsername": "basketfuls",
        "ownerName": "S. L.",
        "ownerUrl": "https://www.pinterest.com/basketfuls/"
      },
      "media": [
        {
          "url": "https://i.pinimg.com/originals/0c/c1/46/0cc14678634e14ece4965635ebed15c4.png",
          "type": "image"
        }
      ]
    }
  }
}