{
  "address": "https://www.pinterest.com/pin/88101736447752971/",
  "dataMode": "json",
  "hotlinkProtected": false,
  "connectionTimeOut": -1,
  "otherPropertiesMap": {
    "CustomFolderName": "basketfuls/landscaping-ideas/long-narrow-gardens",
    "CustomFileName": "88101736447752971",
    "FileExtensionHandleMethod": "workoutExtension",
    "_json": {
      "id": "88101736447752971",
      "url": "https://www.pinterest.com/pin/88101736447752971/",
      "type": "pin",
      "title": "",
      "gridTitle": "60 Small and Fresh Backyard Landscaping Ideas",
      "description": "60 Small and Fresh Backyard Landscaping Ideas",
      "link": "https://architeworks.com/60-small-and-fresh-backyard-landscaping-ideas/",
      "category": "",
      "isStoryPin": false,
      "isCarousel": false,
      "doneByMe": false,
      "favouritedByMe": false,
      "isRepin": true,
      "storyPinItemCount": 0,
      "carouselItemCount": 0,
      "repinCount": 0,
      "favouriteUserCount": 0,
      "board": {
        "url": "https://www.pinterest.com/basketfuls/landscaping-ideas/",
        "name": "landscaping ideas",
        "type": "board",
        "ownerUsername": "basketfuls",
        "ownerName": "S. L.",
        "ownerUrl": "https://www.pinterest.com/basketfuls/"
      },
      "media": [
        {
          "url": "https://i.pinimg.com/originals/79/54/43/7954430ce570ea8f5ff1c053638a73fd.jpg",
          "type": "image"
        }
      ]
    }
  }
}