{
  "address": "https://www.pinterest.com/pin/88101736436502361/",
  "dataMode": "json",
  "hotlinkProtected": false,
  "connectionTimeOut": -1,
  "otherPropertiesMap": {
    "CustomFolderName": "basketfuls/cats-and-kittens",
    "CustomFileName": "88101736436502361",
    "FileExtensionHandleMethod": "workoutExtension",
    "_json": {
      "id": "88101736436502361",
      "url": "https://www.pinterest.com/pin/88101736436502361/",
      "type": "pin",
      "title": "",
      "gridTitle": "",
      "description": "⌂",
      "link": "http://wohnidee.wunderweib.de/garten/artikel-3050124-garten/20-schoene-und-kreative-Gartenideen.html",
      "category": "",
      "isStoryPin": false,
      "isCarousel": false,
      "doneByMe": false,
      "favouritedByMe": false,
      "isRepin": true,
      "storyPinItemCount": 0,
      "carouselItemCount": 0,
      "repinCount": 0,
      "favouriteUserCount": 0,
      "board": {
        "url": "https://www.pinterest.com/basketfuls/cats-and-kittens/",
        "name": "Cats and kittens",
        "type": "board",
        "ownerUsername": "basketfuls",
        "ownerName": "S. L.",
        "ownerUrl": "https://www.pinterest.com/basketfuls/"
      },
      "media": [
        {
          "url": "https://i.pinimg.com/originals/e1/08/8f/e1088f522042f07a47dd5ef0026a810c.jpg",
          "type": "image"
        }
      ]
    }
  }
}