{
  "address": "https://www.pinterest.com/pin/88101736451794084/",
  "dataMode": "json",
  "hotlinkProtected": false,
  "connectionTimeOut": -1,
  "otherPropertiesMap": {
    "CustomFolderName": "basketfuls/autism",
    "CustomFileName": "88101736451794084",
    "FileExtensionHandleMethod": "workoutExtension",
    "_json": {
      "id": "88101736451794084",
      "url": "https://www.pinterest.com/pin/88101736451794084/",
      "type": "pin",
      "title": "Autism",
      "gridTitle": "Autism",
      "description": " ",
      "category": "",
      "isStoryPin": false,
      "isCarousel": false,
      "doneByMe": false,
      "favouritedByMe": false,
      "isRepin": true,
      "storyPinItemCount": 0,
      "carouselItemCount": 0,
      "repinCount": 0,
      "favouriteUserCount": 0,
      "creator": {
        "username": "lifeinautismworld",
        "url": "https://www.pinterest.com/lifeinautismworld/",
        "name": "Life in an Autism World"
      },
      "board": {
        "url": "https://www.pinterest.com/basketfuls/autism/",
        "name": "Autism",
        "type": "board",
        "ownerUsername": "basketfuls",
        "ownerName": "S. L.",
        "ownerUrl": "https://www.pinterest.com/basketfuls/"
      },
      "media": [
        {
          "url": "https://i.pinimg.com/originals/f8/00/b6/f800b61222322428add03b2186293ba2.jpg",
          "type": "image"
        }
      ]
    }
  }
}