{
  "address": "https://www.pinterest.com/pin/88101736447837935/",
  "dataMode": "json",
  "hotlinkProtected": false,
  "connectionTimeOut": -1,
  "otherPropertiesMap": {
    "CustomFolderName": "basketfuls/cottage-dishes",
    "CustomFileName": "88101736447837935",
    "FileExtensionHandleMethod": "workoutExtension",
    "_json": {
      "id": "88101736447837935",
      "url": "https://www.pinterest.com/pin/88101736447837935/",
      "type": "pin",
      "title": "",
      "gridTitle": "Start A Fire",
      "description": "Keep Calm and DIY!: 75 of the Best Shabby Chic Home Decoration Ideas",
      "link": "http://evestanley.stfi.re/2015/05/75-of-best-shabby-chic-home-decoration.html?m=1&sf=agzjyeg#aa",
      "category": "",
      "isStoryPin": false,
      "isCarousel": false,
      "doneByMe": false,
      "favouritedByMe": false,
      "isRepin": true,
      "storyPinItemCount": 0,
      "carouselItemCount": 0,
      "repinCount": 0,
      "favouriteUserCount": 0,
      "board": {
        "url": "https://www.pinterest.com/basketfuls/cottage-dishes/",
        "name": "Cottage Dishes",
        "type": "board",
        "ownerUsername": "basketfuls",
        "ownerName": "S. L.",
        "ownerUrl": "https://www.pinterest.com/basketfuls/"
      },
      "media": [
        {
          "url": "https://i.pinimg.com/originals/e9/95/bc/e995bcf792624574566f77e5e8c2fd43.jpg",
          "type": "image"
        }
      ]
    }
  }
}