{
  "address": "https://www.pinterest.com/pin/88101736437874905/",
  "dataMode": "json",
  "hotlinkProtected": false,
  "connectionTimeOut": -1,
  "otherPropertiesMap": {
    "CustomFolderName": "basketfuls/cottage-garden",
    "CustomFileName": "88101736437874905",
    "FileExtensionHandleMethod": "workoutExtension",
    "_json": {
      "id": "88101736437874905",
      "url": "https://www.pinterest.com/pin/88101736437874905/",
      "type": "pin",
      "title": "",
      "gridTitle": "",
      "description": "english garden - path",
      "link": "http://facebooktrendgames.com/english-garden-path.html",
      "category": "",
      "isStoryPin": false,
      "isCarousel": false,
      "doneByMe": false,
      "favouritedByMe": false,
      "isRepin": true,
      "storyPinItemCount": 0,
      "carouselItemCount": 0,
      "repinCount": 0,
      "favouriteUserCount": 0,
      "board": {
        "url": "https://www.pinterest.com/basketfuls/cottage-garden/",
        "name": "Cottage garden",
        "type": "board",
        "ownerUsername": "basketfuls",
        "ownerName": "S. L.",
        "ownerUrl": "https://www.pinterest.com/basketfuls/"
      },
      "media": [
        {
          "url": "https://i.pinimg.com/originals/4a/25/21/4a2521f66a9ea85136798d4e58937415.jpg",
          "type": "image"
        }
      ]
    }
  }
}