{
  "address": "https://www.pinterest.com/pin/88101736449455542/",
  "dataMode": "json",
  "hotlinkProtected": false,
  "connectionTimeOut": -1,
  "otherPropertiesMap": {
    "CustomFolderName": "basketfuls/hair",
    "CustomFileName": "88101736449455542",
    "FileExtensionHandleMethod": "workoutExtension",
    "_json": {
      "id": "88101736449455542",
      "url": "https://www.pinterest.com/pin/88101736449455542/",
      "type": "pin",
      "title": "39+ Trendy Hair Grey Girl Chic",
      "gridTitle": "39+ Trendy Hair Grey Girl Chic",
      "description": "39+ Trendy Hair Grey Girl Chic",
      "link": "http://womanideas.bloggerium.ru/108289-39-trendy-hair-grey-girl-chic.html",
      "category": "",
      "isStoryPin": false,
      "isCarousel": false,
      "doneByMe": false,
      "favouritedByMe": false,
      "isRepin": true,
      "storyPinItemCount": 0,
      "carouselItemCount": 0,
      "repinCount": 0,
      "favouriteUserCount": 0,
      "creator": {
        "username": "aspenmofo95",
        "url": "https://www.pinterest.com/aspenmofo95/",
        "name": "Wren Blog"
      },
      "board": {
        "url": "https://www.pinterest.com/basketfuls/hair/",
        "name": "Hair",
        "type": "board",
        "ownerUsername": "basketfuls",
        "ownerName": "S. L.",
        "ownerUrl": "https://www.pinterest.com/basketfuls/"
      },
      "media": [
        {
          "url": "https://i.pinimg.com/originals/b3/41/ea/b341eabd7aaa8dbf089f39c2a1d3b9cd.jpg",
          "type": "image"
        }
      ]
    }
  }
}