{
  "address": "https://www.pinterest.com/pin/88101736433774136/",
  "dataMode": "json",
  "hotlinkProtected": false,
  "connectionTimeOut": -1,
  "otherPropertiesMap": {
    "CustomFolderName": "basketfuls/marriagerelationships",
    "CustomFileName": "88101736433774136",
    "FileExtensionHandleMethod": "workoutExtension",
    "_json": {
      "id": "88101736433774136",
      "url": "https://www.pinterest.com/pin/88101736433774136/",
      "type": "pin",
      "title": "",
      "gridTitle": "intentionallyyours.org",
      "description": "Throughout my life, I've made many mistakes. I've done things I'm not proud of, said things that I wish I hadn't said, and I have regrets about choices I've made. However, there is one thing for sure that I definitely do not regret, and that is fighting for my marriage!",
      "link": "http://wp.me/p2D62P-187",
      "category": "",
      "isStoryPin": false,
      "isCarousel": false,
      "doneByMe": false,
      "favouritedByMe": false,
      "isRepin": true,
      "storyPinItemCount": 0,
      "carouselItemCount": 0,
      "repinCount": 0,
      "favouriteUserCount": 0,
      "board": {
        "url": "https://www.pinterest.com/basketfuls/marriagerelationships/",
        "name": "Marriage/relationships",
        "type": "board",
        "ownerUsername": "basketfuls",
        "ownerName": "S. L.",
        "ownerUrl": "https://www.pinterest.com/basketfuls/"
      },
      "media": [
        {
          "url": "https://i.pinimg.com/originals/d1/bb/0e/d1bb0e295855f8f9d793896b1d82978c.jpg",
          "type": "image"
        }
      ]
    }
  }
}