{
  "address": "https://www.pinterest.com/pin/88101736441583618/",
  "dataMode": "json",
  "hotlinkProtected": false,
  "connectionTimeOut": -1,
  "otherPropertiesMap": {
    "CustomFolderName": "basketfuls/breads-also-including-gf-paleo-indian-and-more",
    "CustomFileName": "88101736441583618",
    "FileExtensionHandleMethod": "workoutExtension",
    "_json": {
      "id": "88101736441583618",
      "url": "https://www.pinterest.com/pin/88101736441583618/",
      "type": "pin",
      "title": "",
      "gridTitle": "Easy Egg Bread",
      "description": "Easy Egg Bread | Pillow-y soft, enriched with both eggs and butter, slightly sweet. Great for breakfast with butter and jam or accompanying a comforting meal at dinner time.",
      "link": "http://redstaryeast.com/easy-egg-bread/",
      "category": "",
      "isStoryPin": false,
      "isCarousel": false,
      "doneByMe": false,
      "favouritedByMe": false,
      "isRepin": true,
      "storyPinItemCount": 0,
      "carouselItemCount": 0,
      "repinCount": 0,
      "favouriteUserCount": 0,
      "board": {
        "url": "https://www.pinterest.com/basketfuls/breads-also-including-gf-paleo-indian-and-more/",
        "name": "Breads -also including GF, Paleo, Indian and more..",
        "type": "board",
        "ownerUsername": "basketfuls",
        "ownerName": "S. L.",
        "ownerUrl": "https://www.pinterest.com/basketfuls/"
      },
      "media": [
        {
          "url": "https://i.pinimg.com/originals/67/62/67/67626734506f2ad804b20af61a50090c.jpg",
          "type": "image"
        }
      ]
    }
  }
}