{
  "address": "https://www.pinterest.com/pin/88101736448203388/",
  "dataMode": "json",
  "hotlinkProtected": false,
  "connectionTimeOut": -1,
  "otherPropertiesMap": {
    "CustomFolderName": "basketfuls/low-carb",
    "CustomFileName": "88101736448203388",
    "FileExtensionHandleMethod": "workoutExtension",
    "_json": {
      "id": "88101736448203388",
      "url": "https://www.pinterest.com/pin/88101736448203388/",
      "type": "pin",
      "title": "",
      "gridTitle": "15 Keto Vegan Breakfast Recipes and Ideas",
      "description": "These keto vegetarian and vegan breakfast recipes and ideas make for some delicious, easy and healthy nourishment for low-carb diets! From chia pudding to smoothies, and even vegan quiche, we’ve got you covered with this vegan keto and low-carb recipe round-up! #ketovegan #veganketo #ketobreakfast #veganketobreakfast #ketoveganbreakfast #lowcarbbreakfastrecipes",
      "link": "https://www.moonandspoonandyum.com/blog/vegan-keto-breakfast-recipes-amp-ideas?fbclid=IwAR1GFHO5MCwabusESsXo0XBuc1Xl1Tn1T6v7a541Dp-plQqaAy8RML1KimU",
      "category": "",
      "isStoryPin": false,
      "isCarousel": false,
      "doneByMe": false,
      "favouritedByMe": false,
      "isRepin": true,
      "storyPinItemCount": 0,
      "carouselItemCount": 0,
      "repinCount": 0,
      "favouriteUserCount": 0,
      "creator": {
        "username": "godairyfree",
        "url": "https://www.pinterest.com/godairyfree/",
        "name": "Go Dairy Free"
      },
      "board": {
        "url": "https://www.pinterest.com/basketfuls/low-carb/",
        "name": "Low Carb",
        "type": "board",
        "ownerUsername": "basketfuls",
        "ownerName": "S. L.",
        "ownerUrl": "https://www.pinterest.com/basketfuls/"
      },
      "media": [
        {
          "url": "https://i.pinimg.com/originals/78/78/fd/7878fde23b25004ab844c1d97cc4c6d2.png",
          "type": "image"
        }
      ]
    }
  }
}